{
	"metaData": {
		"Raw data ID": "IMG_D_A6_112851.jpg",
		"copyrighter": "㈜미소정보기술",
		"resolution": "1920X1080",
		"date": "2021-10-16",
		"breed": "몽그렐",
		"age": "2",
		"gender": "M",
		"region": "H",
		"camera type": "IMG",
		"species": "D",
		"lesions": "A6",
		"diagnosis": "",
		"Path": "유증상",
		"identifier": "피부질환",
		"src_path": "/라벨링데이터/반려견/피부/일반카메라/유증상/A6_결절_종괴",
		"label_path": "/라벨링데이터/반려견/피부/일반카메라/유증상/A6_결절_종괴",
		"type": "json",
		"fileformat": "jpg"
	},
	"inspRejectYn": "N",
	"labelingInfo": [
		{
			"polygon": {
				"color": "#6600cc",
				"location": [
					{
						"x1": 1725,
						"y1": 301,
						"x2": 1703,
						"y2": 296,
						"x3": 1661,
						"y3": 314,
						"x4": 1640,
						"y4": 338,
						"x5": 1635,
						"y5": 376,
						"x6": 1672,
						"y6": 401,
						"x7": 1712,
						"y7": 395,
						"x8": 1736,
						"y8": 387,
						"x9": 1769,
						"y9": 351,
						"x10": 1767,
						"y10": 323,
						"x11": 1725,
						"y11": 301
					}
				],
				"label": "A6_결절_종괴",
				"type": "polygon"
			}
		},
		{
			"polygon": {
				"color": "#6600cc",
				"location": [
					{
						"x1": 1280,
						"y1": 230,
						"x2": 1245,
						"y2": 232,
						"x3": 1209,
						"y3": 247,
						"x4": 1194,
						"y4": 266,
						"x5": 1191,
						"y5": 296,
						"x6": 1220,
						"y6": 324,
						"x7": 1260,
						"y7": 327,
						"x8": 1305,
						"y8": 315,
						"x9": 1325,
						"y9": 286,
						"x10": 1326,
						"y10": 268,
						"x11": 1280,
						"y11": 230
					}
				],
				"label": "A6_결절_종괴",
				"type": "polygon"
			}
		},
		{
			"box": {
				"color": "#6600cc",
				"location": [
					{
						"x": 1635,
						"y": 296,
						"width": 134,
						"height": 105
					}
				],
				"label": "A6_결절_종괴",
				"type": "box"
			}
		},
		{
			"box": {
				"color": "#6600cc",
				"location": [
					{
						"x": 1191,
						"y": 230,
						"width": 135,
						"height": 97
					}
				],
				"label": "A6_결절_종괴",
				"type": "box"
			}
		}
	]
}